{
    "Golden State Warriors": 1,
    "Toronto Raptors": 2,
    "Miami Heat": 3,
    "Indiana Pacers": 4,
    "Cleveland Cavaliers": 5,
    "Philadelphia 76ers": 6,
    "Orlando Magic": 7,
    "Milwaukee Bucks": 8,
    "Denver Nuggets": 9,
    "Los Angeles Lakers": 10,
    "Charlotte Hornets": 11,
    "Sacramento Kings": 12,
    "Boston Celtics": 13,
    "Detroit Pistons": 14,
    "Chicago Bulls": 15,
    "Brooklyn Nets": 16,
    "Atlanta Hawks": 17,
    "Portland Trail Blazers": 18,
    "Oklahoma City Thunder": 19,
    "Minnesota Timberwolves": 20,
    "New Orleans Pelicans": 21,
    "San Antonio Spurs": 22,
    "Washington Wizards": 23,
    "New York Knicks": 24,
    "Houston Rockets": 25,
    "Dallas Mavericks": 26,
    "Los Angeles Clippers": 27,
    "Phoenix Suns": 28,
    "Memphis Grizzlies": 29,
    "Utah Jazz": 30
}